{
  "exam_id": 25,
  "questions": [
    {
      "index": 1,
      "real_id": 1711,
      "scraped_id": "000337",
      "question": "Je wilt rechtdoor. Moet je de tram voor laten gaan?",
      "answers": [
        "JA",
        "NEE"
      ],
      "correct_answer_indices": [
        1,
        0
      ],
      "image": "https://members.wegrijden.nl/exams/assets/photo/photo_a/vkf00021354.jpg?v=1634288469"
    },
    {
      "index": 2,
      "real_id": 31206,
      "scraped_id": "011206",
      "question": "Op welke weg heb je bij regen de meeste kans op aquaplaning?",
      "answers": [
        "A\t\tAlleen op weg A.",
        "B\t\tAlleen op weg B.",
        "C\t\tOp beide wegen even groot."
      ],
      "correct_answer_indices": [
        0,
        1,
        0
      ],
      "image": "https://members.wegrijden.nl/exams/assets/photo/photo_a/vkf00023124.jpg?v=1706696804"
    },
    {
      "index": 3,
      "real_id": 29067,
      "scraped_id": "009067",
      "question": "Wie mag eerst?",
      "answers": [],
      "correct_answer_indices": [
        1,
        0,
        0
      ],
      "image": "https://members.wegrijden.nl/exams/assets/photo/photo_a/vkf00016574-2.jpg?v=1584527849"
    },
    {
      "index": 4,
      "real_id": 4475,
      "scraped_id": "001027",
      "question": "Je rijdt een bocht in. Wanneer schakel je?",
      "answers": [
        "A\t\tIn de bocht schakel je naar een lagere versnelling.",
        "B\t\tNa de bocht schakel je naar een lagere versnelling.",
        "C\t\tV贸贸r de bocht schakel je naar een lagere versnelling."
      ],
      "correct_answer_indices": [
        0,
        0,
        1
      ],
      "image": "https://members.wegrijden.nl/exams/assets/photo/photo_a/vkf00013701.jpg?v=1584525186"
    },
    {
      "index": 5,
      "real_id": 4261,
      "scraped_id": "000927",
      "question": "Wanneer verbruik je meer brandstof?",
      "answers": [
        "A\t\tAls je de autoverwarming aan hebt staan.",
        "B\t\tAls je de motor uitschakelt bij korte stops.",
        "C\t\tAls je met een skibox op het dak rijdt."
      ],
      "correct_answer_indices": [
        0,
        0,
        1
      ],
      "image": null
    },
    {
      "index": 6,
      "real_id": 1619,
      "scraped_id": "000307",
      "question": "Je stopt om iemand uit te laten stappen. Mag dat?",
      "answers": [
        "JA",
        "NEE"
      ],
      "correct_answer_indices": [
        0,
        1
      ],
      "image": "https://members.wegrijden.nl/exams/assets/photo/photo_a/vkf00013253.jpg?v=1584525344"
    },
    {
      "index": 7,
      "real_id": 30420,
      "scraped_id": "010420",
      "question": "Onderweg bij koud weer wordt je voorruit geraakt door een steentje en raakt beschadigd. Wat moet je dan doen?",
      "answers": [
        "A\t\tDoorrijden tot je op je bestemming bent.",
        "B\t\tZo snel mogelijk stoppen en hulp inschakelen.",
        "C\t\tDoorrijden en pas stoppen op een parkeerplaats."
      ],
      "correct_answer_indices": [
        1,
        0,
        0
      ],
      "image": "https://members.wegrijden.nl/exams/assets/photo/photo_a/vkf00021923.jpg?v=1657120612"
    },
    {
      "index": 8,
      "real_id": 31059,
      "scraped_id": "011059",
      "question": "Welke verlichting mag of moet je nu overdag voeren? Er kunnen meer antwoorden goed zijn.",
      "answers": [
        "A\t\tDagrijlicht.",
        "B\t\tDimlicht.",
        "C\t\tMistlicht aan de voorzijde.",
        "D\t\tGrootlicht.",
        "E\t\tAchterlicht."
      ],
      "correct_answer_indices": [
        0,
        1,
        1,
        0,
        1
      ],
      "image": "https://members.wegrijden.nl/exams/assets/photo/photo_a/vkf00017347.jpg?v=1695724788"
    },
    {
      "index": 9,
      "real_id": 5282,
      "scraped_id": "001324",
      "question": "Je wilt linksaf. Sorteer je zo goed voor?",
      "answers": [
        "JA",
        "NEE"
      ],
      "correct_answer_indices": [
        1,
        0
      ],
      "image": "https://members.wegrijden.nl/exams/assets/photo/photo_a/vkf00021327.jpg?v=1634288503"
    },
    {
      "index": 10,
      "real_id": 1187,
      "scraped_id": "000185",
      "question": "Je wilt invoegen. Wanneer moet je je richtingaanwijzer aanzetten?",
      "answers": [
        "A\t\tAls je aan het begin van de invoegstrook rijdt.",
        "B\t\tAls je halverwege de invoegstrook rijdt.",
        "C\t\tAls je zeker weet dat je kunt invoegen."
      ],
      "correct_answer_indices": [
        0,
        0,
        1
      ],
      "image": "https://members.wegrijden.nl/exams/assets/photo/photo_a/vkf00013126.jpg?v=1584525226"
    },
    {
      "index": 11,
      "real_id": 31113,
      "scraped_id": "011113",
      "question": "Je komt bij een kruispunt met afbuigende voorrang. Aan welk onderbord kun je herkennen dat andere bestuurders aan jou voorrang moeten verlenen? Er kunnen meer antwoorden goed zijn.",
      "answers": [],
      "correct_answer_indices": [
        1,
        1,
        0,
        0
      ],
      "image": "https://members.wegrijden.nl/exams/assets/photo/photo_a/vkf00022936-1.jpg?v=1695724809"
    },
    {
      "index": 12,
      "real_id": 6255,
      "scraped_id": "001604",
      "question": "Achterop een voertuig zit deze markering. Met welk voertuig heb je te maken?",
      "answers": [
        "A\t\tEen brommobiel.",
        "B\t\tEen bus.",
        "C\t\tEen landbouwtrekker."
      ],
      "correct_answer_indices": [
        0,
        0,
        1
      ],
      "image": "https://members.wegrijden.nl/exams/assets/photo/photo_a/vkf00017216.jpg?v=1584527144"
    },
    {
      "index": 13,
      "real_id": 4256,
      "scraped_id": "000924",
      "question": "Wat weet je over een katalysator?",
      "answers": [
        "A\t\tJe kunt je katalysator beschadigen, als je jouw auto laat slepen om hem weer te starten.",
        "B\t\tJe kunt je katalysator niet beschadigen, als er onverbrande brandstof in de katalysator komt."
      ],
      "correct_answer_indices": [
        1,
        0
      ],
      "image": null
    },
    {
      "index": 14,
      "real_id": 17165,
      "scraped_id": "002709",
      "question": "Wat is hier de juiste volgorde van voor laten gaan?",
      "answers": [],
      "correct_answer_indices": [
        1,
        2,
        3,
        4
      ],
      "image": "https://members.wegrijden.nl/exams/assets/photo/photo_a/vkf00015241-2.jpg?v=1584529894"
    },
    {
      "index": 15,
      "real_id": 31164,
      "scraped_id": "011164",
      "question": "Je wilt linksaf. Moet je de fietsers voor laten gaan?",
      "answers": [
        "JA",
        "NEE"
      ],
      "correct_answer_indices": [
        1,
        0
      ],
      "image": null
    },
    {
      "index": 16,
      "real_id": 16861,
      "scraped_id": "002431",
      "question": "Wat betekent dit symbool?",
      "answers": [
        "A\t\tJe auto heeft een start-stopsysteem.",
        "B\t\tDe motor van je auto kan niet per ongeluk afslaan.",
        "C\t\tJe auto heeft een systeem dat automatisch remt als de afstand tot de voorligger te klein wordt."
      ],
      "correct_answer_indices": [
        1,
        0,
        0
      ],
      "image": "https://members.wegrijden.nl/exams/assets/photo/photo_a/vkf00014261.jpg?v=1584528234"
    },
    {
      "index": 17,
      "real_id": 16902,
      "scraped_id": "002471",
      "question": "Moet je het APK-keuringsbewijs bij je hebben tijdens het rijden?",
      "answers": [
        "JA",
        "NEE"
      ],
      "correct_answer_indices": [
        0,
        1
      ],
      "image": "https://members.wegrijden.nl/exams/assets/photo/photo_a/vkf00014193.jpg?v=1584533594"
    },
    {
      "index": 18,
      "real_id": 16717,
      "scraped_id": "002298",
      "question": "Er staat direct v贸贸r een kruispunt een bord \"voorrangsweg\". Waar bevind je je?",
      "answers": [
        "A\t\tBinnen de bebouwde kom.",
        "B\t\tBuiten de bebouwde kom."
      ],
      "correct_answer_indices": [
        1,
        0
      ],
      "image": "https://members.wegrijden.nl/exams/assets/photo/photo_a/vkf00023022.jpg?v=1706696878"
    },
    {
      "index": 19,
      "real_id": 29923,
      "scraped_id": "009923",
      "question": "Waarom moet je hier de militaire colonne voor laten gaan?",
      "answers": [
        "A\t\tOmdat de militaire colonne van rechts komt.",
        "B\t\tOmdat je een militaire colonne niet mag doorsnijden.",
        "C\t\tOmdat de militaire colonne op een voorrangskruispunt rijdt."
      ],
      "correct_answer_indices": [
        1,
        0,
        0
      ],
      "image": "https://members.wegrijden.nl/exams/assets/photo/photo_a/vkf00024377.jpg?v=1737717385"
    },
    {
      "index": 20,
      "real_id": 16494,
      "scraped_id": "002101",
      "question": "Hoeveel microgram per liter uitgeademde lucht mag het alcoholgehalte van de adem maximaal zijn van iemand die nog geen 5 jaar een rijbewijs heeft?",
      "answers": [],
      "correct_answer_indices": [
        "88"
      ],
      "image": "https://members.wegrijden.nl/exams/assets/photo/photo_a/vkf00010107.jpg?v=1584530321"
    },
    {
      "index": 21,
      "real_id": 6277,
      "scraped_id": "001616",
      "question": "Betekenen deze elektronische signaleringsborden dat dit het einde van de autosnelweg is?",
      "answers": [
        "JA",
        "NEE"
      ],
      "correct_answer_indices": [
        0,
        1
      ],
      "image": "https://members.wegrijden.nl/exams/assets/photo/photo_a/vkf00021148.jpg?v=1625734023"
    },
    {
      "index": 22,
      "real_id": 16683,
      "scraped_id": "002265",
      "question": "Welke invloed heeft vermoeidheid op de oplettendheid van bestuurders?",
      "answers": [
        "A\t\tDe oplettendheid neemt toe.",
        "B\t\tDe oplettendheid neemt af.",
        "C\t\tDit heeft geen invloed op de oplettendheid."
      ],
      "correct_answer_indices": [
        0,
        1,
        0
      ],
      "image": null
    },
    {
      "index": 23,
      "real_id": 29056,
      "scraped_id": "009056",
      "question": "Bij welk verkeersbord is het verboden om met je auto een tractor in te halen?",
      "answers": [],
      "correct_answer_indices": [
        1,
        0,
        0,
        0
      ],
      "image": "https://members.wegrijden.nl/exams/assets/photo/photo_a/vkf00016716-1.jpg?v=1584528347"
    },
    {
      "index": 24,
      "real_id": 31156,
      "scraped_id": "011156",
      "question": "Op welke weg mag je 130 kilometer per uur rijden?",
      "answers": [
        "A\t\tAlleen op weg A.",
        "B\t\tAlleen op weg B.",
        "C\t\tOp weg A en B.",
        "D\t\tGeen van beide."
      ],
      "correct_answer_indices": [
        0,
        0,
        0,
        1
      ],
      "image": "https://members.wegrijden.nl/exams/assets/photo/photo_a/vkf00014938.jpg?v=1584525504"
    },
    {
      "index": 25,
      "real_id": 29123,
      "scraped_id": "009123",
      "question": "Wie mag eerst?",
      "answers": [],
      "correct_answer_indices": [
        1,
        0,
        0
      ],
      "image": "https://members.wegrijden.nl/exams/assets/photo/photo_a/vkf00016636-2.jpg?v=1584528657"
    },
    {
      "index": 26,
      "real_id": 5181,
      "scraped_id": "001277",
      "question": "Je wilt linksaf. Moet je stoppen?",
      "answers": [
        "JA",
        "NEE"
      ],
      "correct_answer_indices": [
        1,
        0
      ],
      "image": "https://members.wegrijden.nl/exams/assets/photo/photo_a/vkf00021398.jpg?v=1634288517"
    },
    {
      "index": 27,
      "real_id": 4703,
      "scraped_id": "001106",
      "question": "Wat betekent dit verkeersbord?",
      "answers": [
        "A\t\tIn deze zone mag je niet parkeren.",
        "B\t\tIn deze zone mag je niet stoppen.",
        "C\t\tOp deze weg mag je aan allebei de kanten niet parkeren."
      ],
      "correct_answer_indices": [
        1,
        0,
        0
      ],
      "image": "https://members.wegrijden.nl/exams/assets/photo/photo_a/vkf00017165.jpg?v=1584528080"
    },
    {
      "index": 28,
      "real_id": 1723,
      "scraped_id": "000341",
      "question": "Je parkeert hier. Mag dat?",
      "answers": [
        "JA",
        "NEE"
      ],
      "correct_answer_indices": [
        1,
        0
      ],
      "image": "https://members.wegrijden.nl/exams/assets/photo/photo_a/vkf00013506.jpg?v=1584530446"
    },
    {
      "index": 29,
      "real_id": 1639,
      "scraped_id": "000314",
      "question": "Het is erg druk op de weg. Je wilt invoegen. Wat kun je het beste doen?",
      "answers": [
        "A\t\tJe rijdt door tot aan het einde van de invoegstrook en daar wacht je totdat je kunt invoegen.",
        "B\t\tJe rijdt zoveel mogelijk met het verkeer mee en zodra het kan probeer je in te voegen.",
        "C\t\tJe zet meteen aan het begin van de invoegstrook je richtingaanwijzer aan en daar probeer je in te voegen."
      ],
      "correct_answer_indices": [
        0,
        1,
        0
      ],
      "image": "https://members.wegrijden.nl/exams/assets/photo/photo_a/vkf00021363.jpg?v=1634288482"
    },
    {
      "index": 30,
      "real_id": 31376,
      "scraped_id": "011376",
      "question": "Mag je de vrachtauto nu voorbijrijden?",
      "answers": [
        "JA",
        "NEE"
      ],
      "correct_answer_indices": [
        0,
        1
      ],
      "image": null
    },
    {
      "index": 31,
      "real_id": 5211,
      "scraped_id": "001293",
      "question": "Je wilt de weg naar links volgen. Moet je de fietser voor laten gaan?",
      "answers": [
        "JA",
        "NEE"
      ],
      "correct_answer_indices": [
        1,
        0
      ],
      "image": "https://members.wegrijden.nl/exams/assets/photo/photo_a/vkf00013965.jpg?v=1584526889"
    },
    {
      "index": 32,
      "real_id": 3530,
      "scraped_id": "000664",
      "question": "Je rijdt op een goed verlichte weg. Dan sla je een donkere weg in. Waarom kan dit gevaarlijk zijn?",
      "answers": [
        "A\t\tJe hebt even een paar seconden nodig om te wennen aan het donker.",
        "B\t\tJe ziet bestuurders op de donkere weg bijna nooit op tijd.",
        "C\t\tIn een donkere straat zijn donkere obstakels niet te zien."
      ],
      "correct_answer_indices": [
        1,
        0,
        0
      ],
      "image": null
    },
    {
      "index": 33,
      "real_id": 29047,
      "scraped_id": "009047",
      "question": "Welk symbool geeft aan dat er iets mis is met het ABS systeem?",
      "answers": [],
      "correct_answer_indices": [
        0,
        0,
        1,
        0
      ],
      "image": "https://members.wegrijden.nl/exams/assets/photo/photo_a/vkf00016741-1.jpg?v=1584526206"
    },
    {
      "index": 34,
      "real_id": 547,
      "scraped_id": "000026",
      "question": "Een bus wil wegrijden bij een bushalte. De bus heeft de richtingaanwijzer aangezet. Wanneer moet je de bus voor laten gaan?",
      "answers": [
        "A\t\tAls de halte binnen de bebouwde kom ligt.",
        "B\t\tAls de halte binnen of buiten de bebouwde kom ligt.",
        "C\t\tAls de halte buiten de bebouwde kom ligt."
      ],
      "correct_answer_indices": [
        1,
        0,
        0
      ],
      "image": "https://members.wegrijden.nl/exams/assets/photo/photo_a/vkf00017305-1.jpg?v=1584525983"
    },
    {
      "index": 35,
      "real_id": 31327,
      "scraped_id": "011327",
      "question": "Er zit een barst in een van de achterlichten van de auto. Je hebt deze met doorzichtig plakband gerepareerd. Mag je gaan rijden?",
      "answers": [
        "JA",
        "NEE"
      ],
      "correct_answer_indices": [
        1,
        0
      ],
      "image": "https://members.wegrijden.nl/exams/assets/photo/photo_a/vkf00023158.jpg?v=1717592976"
    },
    {
      "index": 36,
      "real_id": 5591,
      "scraped_id": "001956",
      "question": "Wat bepaalt de minimale volgafstand die je moet aanhouden?",
      "answers": [
        "A\t\tDe lengte van je voertuig.",
        "B\t\tDe weersomstandigheden.",
        "C\t\tHet merk banden wat gemonteerd is."
      ],
      "correct_answer_indices": [
        0,
        1,
        0
      ],
      "image": "https://members.wegrijden.nl/exams/assets/photo/photo_a/vkf00013121.jpg?v=1584526024"
    },
    {
      "index": 37,
      "real_id": 29812,
      "scraped_id": "009812",
      "question": "Wat is hier de juiste volgorde van voor laten gaan?",
      "answers": [],
      "correct_answer_indices": [
        1,
        2
      ],
      "image": "https://members.wegrijden.nl/exams/assets/photo/photo_a/vkf00019796-2.jpg?v=1584528821"
    },
    {
      "index": 38,
      "real_id": 3599,
      "scraped_id": "000700",
      "question": "Welk verkeersbord geeft een eenrichtingsweg aan?",
      "answers": [
        "A\t\tAlleen verkeersbord 1.",
        "B\t\tAlleen verkeersbord 2.",
        "C\t\tVerkeersbord 1 en 2."
      ],
      "correct_answer_indices": [
        0,
        0,
        1
      ],
      "image": "https://members.wegrijden.nl/exams/assets/photo/photo_a/vkf00020033.jpg?v=1584715154"
    },
    {
      "index": 39,
      "real_id": 16439,
      "scraped_id": "002063",
      "question": "Je wilt rechtdoor. Mag je deze rijstrook blijven volgen?",
      "answers": [
        "JA",
        "NEE"
      ],
      "correct_answer_indices": [
        1,
        0
      ],
      "image": "https://members.wegrijden.nl/exams/assets/photo/photo_a/vkf00021376.jpg?v=1634288502"
    },
    {
      "index": 40,
      "real_id": 4592,
      "scraped_id": "001055",
      "question": "Wanneer is bellen tijdens het rijden het gevaarlijkst?",
      "answers": [
        "A\t\tAls je de telefoon aan je oor houdt.",
        "B\t\tAls je door het gesprek wordt afgeleid."
      ],
      "correct_answer_indices": [
        0,
        1
      ],
      "image": "https://members.wegrijden.nl/exams/assets/photo/photo_a/vkf00017198.jpg?v=1584525199"
    },
    {
      "index": 41,
      "real_id": 4907,
      "scraped_id": "001217",
      "question": "Wat is vervelend voor ander verkeer?",
      "answers": [
        "A\t\tDat je langzamer gaat rijden in dichte mist.",
        "B\t\tDat je niet inhaalt terwijl dit wel mag.",
        "C\t\tDat je niet veel harder rijdt dan de voertuigen die je inhaalt."
      ],
      "correct_answer_indices": [
        0,
        0,
        1
      ],
      "image": null
    },
    {
      "index": 42,
      "real_id": 1008,
      "scraped_id": "000119",
      "question": "Wat betekent dit verkeersbord?",
      "answers": [
        "A\t\tDit is het einde van de zone waarin je alleen met een parkeerschijf mag parkeren.",
        "B\t\tDit is het einde van de zone waarin je maximaal 30 kilometer per uur mag rijden.",
        "C\t\tDit is het einde van de zone waarin je niet mag parkeren."
      ],
      "correct_answer_indices": [
        0,
        0,
        1
      ],
      "image": "https://members.wegrijden.nl/exams/assets/photo/photo_a/vkf00017068.jpg?v=1584527822"
    },
    {
      "index": 43,
      "real_id": 4911,
      "scraped_id": "001220",
      "question": "Op het volgende kruispunt wil je afslaan. Op hoeveel meter voor het kruispunt geef je richting aan?",
      "answers": [
        "A\t\t50 meter.",
        "B\t\t100 meter.",
        "C\t\t200 meter."
      ],
      "correct_answer_indices": [
        0,
        0,
        1
      ],
      "image": "https://members.wegrijden.nl/exams/assets/photo/photo_a/vkf00021233.jpg?v=1625734425"
    },
    {
      "index": 44,
      "real_id": 31369,
      "scraped_id": "011369",
      "question": "In welke situatie mag je rechts inhalen? Er kunnen meer antwoorden goed zijn!",
      "answers": [],
      "correct_answer_indices": [
        1,
        1,
        0,
        0
      ],
      "image": "https://members.wegrijden.nl/exams/assets/photo/photo_a/vkf00023633-1.jpg?v=1717592976"
    },
    {
      "index": 45,
      "real_id": 31348,
      "scraped_id": "011348",
      "question": "Wat doe je?",
      "answers": [
        "A\t\tJe rijdt de bussen snel voorbij.",
        "B\t\tJe rijdt de bussen rustig voorbij.",
        "C\t\tJe stopt en laat het busje voorgaan."
      ],
      "correct_answer_indices": [
        0,
        1,
        0
      ],
      "image": null
    },
    {
      "index": 46,
      "real_id": 31101,
      "scraped_id": "011101",
      "question": "Voor welke voertuigen heb je GEEN rijbewijs nodig? Er kunnen meer antwoorden goed zijn.",
      "answers": [
        "A\t\tSegway.",
        "B\t\tSnorfiets.",
        "C\t\tSpeed-pedelec.",
        "D\t\tElektrische fiets.",
        "E\t\tScootmobiel.",
        "F\t\tLandbouwtrekker of brommobiel."
      ],
      "correct_answer_indices": [
        1,
        0,
        0,
        1,
        1,
        0
      ],
      "image": null
    },
    {
      "index": 47,
      "real_id": 5204,
      "scraped_id": "001287",
      "question": "Je bent per ongeluk deze weg ingereden. Mag je hier keren?",
      "answers": [
        "JA",
        "NEE"
      ],
      "correct_answer_indices": [
        1,
        0
      ],
      "image": "https://members.wegrijden.nl/exams/assets/photo/photo_a/vkf00013887.jpg?v=1584526465"
    },
    {
      "index": 48,
      "real_id": 3976,
      "scraped_id": "000820",
      "question": "Je rijdt op een dijk. Wat is het grootste gevaar?",
      "answers": [
        "A\t\tJe kunt niet goed zien hoe de vorm van de weg is.",
        "B\t\tJe kunt niet goed zien of er voetgangers lopen.",
        "C\t\tJe ziet bestuurders die langzaam rijden te laat."
      ],
      "correct_answer_indices": [
        1,
        0,
        0
      ],
      "image": null
    },
    {
      "index": 49,
      "real_id": 31939,
      "scraped_id": "011939",
      "question": "Het is na 19 uur. Wat is de maximum-snelheid van een auto met fietsendrager op een autosnelweg buiten de bebouwde kom?",
      "answers": [],
      "correct_answer_indices": [
        "130"
      ],
      "image": "https://members.wegrijden.nl/exams/assets/photo/photo_a/vkf00016813.jpg?v=1584527219"
    },
    {
      "index": 50,
      "real_id": 3292,
      "scraped_id": "000594",
      "question": "Wat doe je als je na dit verkeersbord groot wild op de weg ziet?",
      "answers": [
        "A\t\tJe gaat langzamer rijden.",
        "B\t\tJe wijkt direct uit om het dier niet te raken.",
        "C\t\tJe remt en zet het groot licht uit."
      ],
      "correct_answer_indices": [
        0,
        0,
        1
      ],
      "image": "https://members.wegrijden.nl/exams/assets/photo/photo_a/vkf00017090.jpg?v=1584525518"
    }
  ]
}